milescoder/__init__.py
milescoder/converter.py
milescoder/models.py
milescoder-0.1.3.dist-info/licenses/LICENSE
milescoder-0.1.3.dist-info/METADATA
milescoder-0.1.3.dist-info/WHEEL
milescoder-0.1.3.dist-info/top_level.txt
milescoder-0.1.3.dist-info/RECORD
