Metadata-Version: 2.4
Name: milescoder
Version: 0.1.3
Summary: A Python package for encoding and decoding MILES (Material Input Line Entry System) strings - a standardized notation system for describing comprehensive material properties in a compact, machine-readable format.
Author-email: Tim Würger <tim.wuerger@hereon.de>
License-Expression: MIT
Project-URL: Homepage, https://github.com/MILES4Materials/milescoder
Project-URL: Issues, https://github.com/MILES4Materials/milescoder/issues
Classifier: Programming Language :: Python :: 3
Classifier: Operating System :: OS Independent
Requires-Python: >=3.9
License-File: LICENSE
Requires-Dist: pydantic>=1.8.0
Dynamic: license-file
